MANIFEST.in
README.txt
requirements.txt
setup.py
test_requirements.txt
version.txt
cloudshell/__init__.py
cloudshell/networking/__init__.py
cloudshell/networking/ericsson/__init__.py
cloudshell/networking/ericsson/ipos/__init__.py
cloudshell/networking/ericsson/ipos/ericsson_ipos_configuration.py
cloudshell/networking/ericsson/ipos/ericsson_ipos_resource_driver.py
cloudshell/networking/ericsson/ipos/autoload/__init__.py
cloudshell/networking/ericsson/ipos/autoload/ericsson_ipos_snmp_autoload.py
cloudshell/networking/ericsson/ipos/autoload/mib/ERICSSON-ROUTER-IP-BIND-MIB.py
cloudshell/networking/ericsson/ipos/autoload/mib/ERICSSON-ROUTER-PRODUCT-MIB.py
cloudshell/networking/ericsson/ipos/autoload/mib/ERICSSON-ROUTER-SMI.py
cloudshell/networking/ericsson/ipos/autoload/mib/ERICSSON-ROUTER-TC.py
cloudshell/networking/ericsson/ipos/autoload/mib/ERICSSON-TOP-MIB.py
cloudshell/networking/ericsson/ipos/autoload/mib/__init__.py
cloudshell_networking_ericsson_ipos.egg-info/PKG-INFO
cloudshell_networking_ericsson_ipos.egg-info/SOURCES.txt
cloudshell_networking_ericsson_ipos.egg-info/dependency_links.txt
cloudshell_networking_ericsson_ipos.egg-info/requires.txt
cloudshell_networking_ericsson_ipos.egg-info/top_level.txt