Metadata-Version: 1.0
Name: cloudshell-networking-ericsson-ipos
Version: 1.0.21
Summary: QualiSystems networking Ericsson IPOS specific Package
Home-page: http://www.qualisystems.com/
Author: QualiSystems
Author-email: info@qualisystems.com
License: UNKNOWN
Platform: UNKNOWN
